hooks/__init__.py
hooks/add_pre_commit_hook.py
hooks/cf_gh_pages_dns_records.py
hooks/dev_extras_required.py
hooks/file_check_lines.py
hooks/nameservers_endswith.py
hooks/root_editorconfig_required.py
hooks/wavelint.py
mondeja_pre_commit_hooks-1.8.0.dist-info/LICENSE
mondeja_pre_commit_hooks-1.8.0.dist-info/METADATA
mondeja_pre_commit_hooks-1.8.0.dist-info/WHEEL
mondeja_pre_commit_hooks-1.8.0.dist-info/entry_points.txt
mondeja_pre_commit_hooks-1.8.0.dist-info/top_level.txt
mondeja_pre_commit_hooks-1.8.0.dist-info/RECORD
