Metadata-Version: 2.1
Name: mondeja-pre-commit-hooks
Version: 1.8.0
Summary: My own useful pre-commit hooks
Home-page: https://github.com/mondeja/pre-commit-hooks
Author: Alvaro Mondejar Rubio
Author-email: mondejar1994@gmail.com
License: BSD-3-Clause
Platform: UNKNOWN
Classifier: License :: OSI Approved :: BSD License
Classifier: Programming Language :: Python
Classifier: Programming Language :: Python :: 3
Classifier: Programming Language :: Python :: 3 :: Only
Classifier: Programming Language :: Python :: 3.6
Classifier: Programming Language :: Python :: 3.7
Classifier: Programming Language :: Python :: 3.8
Classifier: Programming Language :: Python :: 3.9
Classifier: Programming Language :: Python :: 3.10
Requires-Python: >=3.6.1
Provides-Extra: dev
Requires-Dist: bump2version (==1.0.1) ; extra == 'dev'
Requires-Dist: cloudflare (==2.8.15) ; extra == 'dev'
Requires-Dist: dnspython (==2.1.0) ; extra == 'dev'
Requires-Dist: pytest (==6.2.4) ; extra == 'dev'
Requires-Dist: pytest-cov (==2.12.1) ; extra == 'dev'
Requires-Dist: pyyaml (==5.4.1) ; extra == 'dev'
Requires-Dist: toml (==0.10.2) ; extra == 'dev'
Requires-Dist: waves (==0.2.5) ; extra == 'dev'
Provides-Extra: test
Requires-Dist: cloudflare (==2.8.15) ; extra == 'test'
Requires-Dist: dnspython (==2.1.0) ; extra == 'test'
Requires-Dist: pytest (==6.2.4) ; extra == 'test'
Requires-Dist: pytest-cov (==2.12.1) ; extra == 'test'
Requires-Dist: pyyaml (==5.4.1) ; extra == 'test'
Requires-Dist: toml (==0.10.2) ; extra == 'test'
Requires-Dist: waves (==0.2.5) ; extra == 'test'
